Workbook

Sheet Caratula
C2: INFORMACIÓN GENERAL DEL PLAN OPERATIVO DEL PLAN DE NEGOCIOS DE ADOPCIÓN DE TECNOLOGÍA
A4: INFORMACIÓN GENERAL DEL PLAN DE NEGOCIO
A5: N° de Convenio: | C5: 012-2025-MIDAGRI-AGROIDEAS | E5: N° Acta de CD: | G5: 100-2023 | H5: Periodo de Trabajo: | J5: 12 meses
A7: Nombre de la Organización: | C7: ASOCIACION DE PRODUCTORES AGROPECUARIOS MICROCUENCA NORTE RIO NUÑOA | H7: RUC: | J7: 20448433316 | K7: N° de Socios: | L7: 27
A8: Nombre del Plan de Negocios: | C8: MEJORAMIENTO DEL MANEJO PRUDUCTIVO DE LA ALPACA | H8: Producto o Actividad: | J8: Engorde y venta de alpacas en Pie | K8: Has según PN: | L8: 2360.21
A10: GEOREFERENCIACIÓN DEL PLAN DE NEGOCIO
A11: Departamento | C11: Provincia | E11: Distrito | G11: Localidad | I11: Coordenadas Geográficas
A12: Puno | C12: Melgar | E12: Nuñoa | G12: Carabaya | I12: Latitud | K12: Longitud
A15: CRONOGRAMA DE EJECUCIÓN | G15: PLAN DE COFINANCIAMIENTO
B16: POA 1 | G16: CO Financiamiento | I16: POA 1: Presupuesto S/. | K16: %
B17: Fecha de Inicio | D17: Fecha de Fin | G17: AGROIDEAS (S/. ) | I17: =I19*K17 -> 409882.4 | K17: 0.8
A18: PC1 | B18: 45749 | D18: 02//10/2025 | G18: OA (S/. ) | I18: =I19*K18 -> 102470.6 | K18: 0.2
A19: PC2 | B19: 45933 | D19: 46114 | G19: Total (S/. ) | I19: ='Formato 01'!M10 -> 512353 | K19: =SUM(K17:K18) -> 1
I21: =8000+230256+63162.88 -> 301418.88
A23: Representante Legal de la OA | E23: Coordinador de la UR | I23: Jefatura de la UM
A32: Firma | E32: Firma | I32: Firma
G38: 987330453

Sheet Formato 01
J1: =6.48*250 -> 1620
C3: FORMATO 01 - PLAN DE ADQUISICIONES DE EQUIPOS, INSUMOS Y SERVICIOS
C4: POA: | E4: PRIMER POA | N4: =18900-3240 -> 15660
C5: Nombre OA: | E5: =+Caratula!C7 -> ASOCIACION DE PRODUCTORES AGROPECUARIOS MICROCUENCA NORTE RIO NUÑOA | N5: =30240-11664 -> 18576 | O5: =1296+11664 -> 12960
C6: RUC: | E6: =+Caratula!J7 -> 20448433316 | N6: =1620+30240 -> 31860 | O6: =324+18576 -> 18900
C7: Plan de Negocios: | E7: =+Caratula!C8 -> MEJORAMIENTO DEL MANEJO PRUDUCTIVO DE LA ALPACA
B8: Objetivo Especifico / Actividad | G8: Especificación del Bien / Servicio | J8: PRESUPUESTO APROBADO EN EL PLAN DE NEGOCIO | N8: PARTICIPACIÓN PRESUPUESTAL
J9: Unidad de Medida | K9: Cantidad | L9: Costo Unitario S/. | M9: Costo Total Aprobado S/. | N9: OPA S/. | O9: AGROIDEAS S/. | P9: PASO CRÍTICO
C10: TOTAL GENERAL | M10: =+M12+M20+M24+M26 -> 512353 | N10: =+N12+N20+N24+N26 -> 102470.6 | O10: =+O12+O20+O24+O26 -> 409882.4
M11: Porcentaje de Cofinanciamiento | N11: =+N10/M10 -> 0.2 | O11: =+O10/M10 -> 0.8
B12: 1.1. Mecanizacion del Proceso productivo de la Quinua | C12: 1.1. Aplicar Técnicas de manejo adecuado de los rebaños de alpacas que permita incrementar gradualmente la ganacia de peso diario de 0.08 kg/día a 0.15 kg/día/ alpaca al 5to año | J12: Sub Total 1.1. | M12: =SUM(M13:M19) -> 350595 | N12: =SUM(N13:N19) -> 70119 | O12: =SUM(O13:O19) -> 280476
B13: Mallas ganaderas de 9 hilos por 100 metros | G13: Rollo de 100 m 9 hilos*1.20 altura Diámetro de alambre 2.15 mm Recubrimiento de alambre de zinc 90% | J13: Rollos | K13: 432 | L13: 430 | M13: =+K13*L13 -> 185760 | N13: =+M13*0.2 -> 37152 | O13: =+M13*0.8 -> 148608 | P13: I PC
B14: Postes Metálicos de 1.98m x 1.15"con ancla tipo flecha de acero, acabado y pintado | G14: Material: Metálico - Dimensiones: 1.98 m x 1.15" ancla tipo flecha de acero acabado y pintado con pintura anticorrosiva - Tipo de instalación: lleva un ancla en la parte inferior tipo flecha (para fácil empotramiento en el terreno) - Intalación de Malla: compatible para instalación de alambres de malla galvanizada de 9 hilos | J14: Unidad | K14: 4320 | L14: 24 | M14: =+K14*L14 -> 103680 | N14: =+M14*0.2 -> 20736 | O14: =+M14*0.8 -> 82944 | P14: I PC
B15: Tecle 2T | G15: Material: acero - Ganchos forjados de acero al medio carbono con cierres de seguridad - Engrane de acero de doble cremallera para mayor resistencia - Botón de seguridad que libera el mecanismo - Ideal para tensado de cables y mallas | J15: Unidad | K15: 27 | L15: 100 | M15: =+K15*L15 -> 2700 | N15: =+M15*0.2 -> 540 | O15: =+M15*0.8 -> 2160 | P15: I PC
C16: Gripples medianos | G16: Diámetro del Alambre: 2mm a 3,25mm - Bolsa de 20 Unidades | J16: Unidad | K16: 2916 | L16: 5 | M16: =+K16*L16 -> 14580 | N16: =+M16*0.2 -> 2916 | O16: =+M16*0.8 -> 11664 | P16: I PC
B17: Grapha Galvanizada 1" | G17: Grapas Galvanizadas x 1kg Fabricadas en acero con acabado galvanizado, resistente a la corrosión - Corrugadas con diseño en "U" para mayor fijación en alambres o mallas de acero - Puntas afiladas para una excelente horadación | J17: Kg | K17: 162 | L17: 10 | M17: =+K17*L17 -> 1620 | N17: =+M17*0.2 -> 324 | O17: =+M17*0.8 -> 1296 | P17: I PC
B18: Puertas | G18: Dimensiones 120x200 - Tubo galvanizado de 1/2 - Malla alambre galvanizado N° 10 | J18: Unidad | K18: 108 | L18: 390 | M18: =+K18*L18 -> 42120 | N18: =+M18*0.2 -> 8424 | O18: =+M18*0.8 -> 33696 | P18: I PC | Q18: =O18+O23 -> 89856
B19: Yeso Bolsa 30Kg | G19: Bolsa de 25kg | J19: Bolsa | K19: 13.5 | L19: 10 | M19: =+K19*L19 -> 135 | N19: =+M19*0.2 -> 27 | O19: =+M19*0.8 -> 108 | P19: I PC
C20: 1.2. Ampliar la oferta forrajera con la instalación de 54 ha de alfalfa y dactilys en la asociación al 2do año | J20: Sub Total 1.2. | M20: =SUM(M21:M23) -> 126900 | N20: =SUM(N21:N23) -> 25380 | O20: =SUM(O21:O23) -> 101520
C21: Semilla de Alfalfa | G21: Variedad: W350 Presentación: saco de 25kg - Dormancia: 3.8 - Producción: 22 a 28 LMS/Ha/año - Longevidad: larga duración - Proteina: 22% - Digestibilidad: 70% - Humedad: 5-12% - Germinación mínima 90% - Pureza física: 99% | J21: Kg | K21: 1350 | L21: 40 | M21: =+K21*L21 -> 54000 | N21: =+M21*0.2 -> 10800 | O21: =+M21*0.8 -> 43200 | P21: IIPC
C22: Semilla de Dactilys Glomerata | G22: Variedad: Glomerata Potomac - Presentación: saco de 50 Kg - Humedad: 5-12% - Germinación mínima 85% - Pureza física: 99% | J22: Kg | K22: 108 | L22: 25 | M22: =+K22*L22 -> 2700 | N22: =+M22*0.2 -> 540 | O22: =+M22*0.8 -> 2160 | P22: =$P$21 -> IIPC
C23: Guano de las islas | G23: Presentación: saco de polipropileno con capacidad de 48 Kg - El guano de las islas presenta en forma de polvo de granulación uniforme - De color gris amarillento verdoso - Con olor fuerte a vapores amoniacales - Contiene una humedad de 16 - 18% | J23: Sacos | K23: 1080 | L23: 65 | M23: =+K23*L23 -> 70200 | N23: =+M23*0.2 -> 14040 | O23: =+M23*0.8 -> 56160 | P23: IIPC
C24: 1.3.Reducir el porcentaje de mortalidad de 4% a 2% al 2do año | J24: Sub Total 1.3. | M24: =SUM(M25:M25) -> 6858 | N24: =SUM(N25:N25) -> 1371.6 | O24: =SUM(O25:O25) -> 5486.4
B25: Kit Veterinario | G25: Pistola dosificadora automática x 30ml - Aguja metálica 18 x 1 1/2 - Jeringa TP x 50 - Termómetro veterinario digital | J25: Global | K25: 27 | L25: 254 | M25: =+K25*L25 -> 6858 | N25: =+M25*0.2 -> 1371.6 | O25: =+M25*0.8 -> 5486.4 | P25: IPC
C26: 1.4. Desarrollar capacidades para una eficiente gestión comercial de organización | J26: Sub Total 1.5. | M26: =SUM(M27:M28) -> 28000 | N26: =M26*0.2 -> 5600 | O26: =M26*0.8 -> 22400
B27: Coordinador del PNT | G27: Modalidad: servicio contratado por 12 meses. Perfil profesional Profesional titulado en Medicina Veterinaria y Zootecnia, Ingeniero zootecnista, Ingeniero agrónomo Experiencia General: seis (6) años en proyectos productivos de desarrollo pecuario Expericiencia Específica: Mínimo 3 años en la implementación de proyectos productivos de desarrollo alpaquero. Conocimiento del desarrollo de la cadena productiva de alpacas en infraestructura productiva, praderas nativas, sanidad animal, manejo de rebaño, manejo reproductivo, mejoramiento genético, campaña de acopio de fibra, gestión organizativa y articulación comercial Idiomas: Castellano y de preferencia dominio de quechua Funciones principales: 1. Valida y reconstruye la línea base de la organización 2. Vela por el cumplimiento de los objetivos y POA del PNT 3. Asesora y acompaña a la junta directiva en la adquisición de bienes y servicios 4. Elabora el calendario de manejo y sanitario para la organización 5. Elabora el Plan de Capacitación del PNT 6. Elabora el Plan de Asistencia Técnica 7. Desarrollo la asistencia técnica personalizada a cada beneficiario 8. Planifica e implementa las campañas técnicas de empadre controlado, parición, destete, selección y saca de animales. 9. Planifica y ejecuta las campañas sanitarias 10. Elabora los informes del RTF de la organización y validad por la directiva alcanza el programa 11. Elabora su informe mensual de trabajo a la presidencia de la organización para su validación gestión respectiva | J27: Mes | K27: 9 | L27: 2000 | M27: =+K27*L27 -> 18000 | N27: =+M27*0.2 -> 3600 | O27: =+M27*0.8 -> 14400 | P27: I PC y II PC
B28: Formulación del PNT | G28: Perfil del Profesional: - Profesional en ciencias agrarias: Médico veterinario y zootecnista, Ingeniero zootecnista e Ingeniero Agrónomo Experiencia: - General: Experiencia profesional de cinco (05) años en el sector agrario público y privado - Específica: Experiencia de tres (03) años en formulación de planes de negocios Funciones: - Levantar información de campo, para conocer el estado de la línea de base de la organización - Sostener reuniones con los productores para obtener información complementaria a la línea de base a nivel individual y organizacional - Sostener reuniones para verificar el nivel tecnológico en el que se encuentra la organización y verificar las deficiencias en bienes y servicios, que no permiten un avance competitivo de la organización - Evaluación de las fases de la cadena del agronegocio de la organización e identificación de los cuellos de botella tecnológicos para ser cubiertos con bienes y servicios, así como las oportunidades de mercado solicitados en el PNT - Elaboración del PNT de tecnología y exposición a la organización en pleno para su aprobación Tiempo de Contrato: desde la presentación de la solicitud a AGROIDEAS hasla ta aprobación a nivel de consejo directivo | J28: PNT | K28: 1 | L28: 10000 | M28: =+K28*L28 -> 10000 | N28: =+M28*0.2 -> 2000 | O28: =+M28*0.8 -> 8000 | P28: I PC
C30: Fecha y Hora : 28/04/2025 05:20 p.m.

Sheet Formato 02A
B5: FORMATO 02A - PROGRAMACIÓN FÍSICA DE ACTIVIDADES POR PASO CRITICO
B6: POA: | D6: PRIMER POA
B7: Nombre OA: | D7: =+Caratula!C7 -> ASOCIACION DE PRODUCTORES AGROPECUARIOS MICROCUENCA NORTE RIO NUÑOA
B8: RUC: | D8: =+Caratula!J7 -> 20448433316
B9: Plan de Negocios: | D9: =+Caratula!C8 -> MEJORAMIENTO DEL MANEJO PRUDUCTIVO DE LA ALPACA
B11: # | C11: OBJETIVO ESPECIFICO | E11: ACTIVIDAD | F11: MEDIO DE VERIFICACIÓN | G11: UNIDAD DE MEDIDA | H11: META | I11: PC 01 | O11: PC 02
I12: 45749 | J12: 45779 | K12: 45810 | L12: 45840 | M12: 45871 | N12: 45902 | O12: 45932 | P12: 45963 | Q12: 45993 | R12: 46024 | S12: 46055 | T12: 46083
B13: 1 | C13: ='Formato 01'!C12:I12 -> 1.1. Aplicar Técnicas de manejo adecuado de los rebaños de alpacas que permita incrementar gradualmente la ganacia de peso diario de 0.08 kg/día a 0.15 kg/día/ alpaca al 5to año | E13: ='Formato 01'!B13 -> Mallas ganaderas de 9 hilos por 100 metros | F13: Acta de Entrega Recepción | G13: =+'Formato 01'!J13 -> Rollos | H13: =+'Formato 01'!K13 -> 432 | J13: =H13 -> 432
E14: ='Formato 01'!B14 -> Postes Metálicos de 1.98m x 1.15"con ancla tipo flecha de acero, acabado y pintado | F14: Acta de Entrega Recepción | G14: =+'Formato 01'!J14 -> Unidad | H14: =+'Formato 01'!K14 -> 4320 | J14: =H14 -> 4320
E15: ='Formato 01'!B15 -> Tecle 2T | F15: Acta de Entrega Recepción | G15: =+'Formato 01'!J15 -> Unidad | H15: =+'Formato 01'!K15 -> 27 | J15: =H15 -> 27
E16: Gripples medianos | F16: Acta de Entrega Recepción | G16: =+'Formato 01'!J16 -> Unidad | H16: 90 | J16: =H16 -> 90 | Q16: 90
E17: ='Formato 01'!B17 -> Grapha Galvanizada 1" | F17: Acta de Entrega Recepción | G17: =+'Formato 01'!J17 -> Kg | H17: =+'Formato 01'!K17 -> 162 | J17: =H17 -> 162
E18: Puertas | F18: Acta de Entrega Recepción | G18: =+'Formato 01'!J18 -> Unidad | H18: =+'Formato 01'!K18 -> 108 | J18: =H18 -> 108
E19: Yeso Bolsa 30Kg | F19: Acta de Entrega Recepción | G19: Bolsa | H19: =+'Formato 01'!K19 -> 13.5 | J19: =H19 -> 13.5
B20: 2 | C20: ='Formato 01'!C20:I20 -> 1.2. Ampliar la oferta forrajera con la instalación de 54 ha de alfalfa y dactilys en la asociación al 2do año | E20: Semilla de Alfalfa | F20: Acta de Entrega Recepción | G20: Kg | H20: ='Formato 01'!K21 -> 1350 | N20: =H20 -> 1350
E21: Semilla de Dactilys Glomerata | F21: Acta de Entrega Recepción | G21: Kg | H21: ='Formato 01'!K22 -> 108 | N21: =H21 -> 108
E22: Guano de las islas | F22: Acta de Entrega Recepción | G22: Sacos | H22: ='Formato 01'!K23 -> 1080 | N22: =H22 -> 1080
B23: 3 | C23: ='Formato 01'!C24:I24 -> 1.3.Reducir el porcentaje de mortalidad de 4% a 2% al 2do año | E23: ='Formato 01'!B25 -> Kit Veterinario | F23: Acta de Entrega Recepción | G23: =+'Formato 01'!J25 -> Global | H23: =+'Formato 01'!K25 -> 27 | N23: =H23 -> 27
B24: 4 | C24: ='Formato 01'!C26:I26 -> 1.4. Desarrollar capacidades para una eficiente gestión comercial de organización | E24: ='Formato 01'!B27 -> Coordinador del PNT | F24: Informe | G24: MES | H24: =+'Formato 01'!K27 -> 9 | L24: 1 | M24: 1 | N24: 1 | O24: 1 | P24: 1 | Q24: 1 | R24: 1 | S24: 1 | T24: 1
E25: ='Formato 01'!B28 -> Formulación del PNT | F25: Informe | G25: PNT | H25: =+'Formato 01'!K28 -> 1 | J25: 1
C28: Fecha y Hora : 28/04/2025 05:20 p.m.

Sheet Formato 02B
B5: FORMATO 02B - PROGRAMACIÓN FINANCIERA DE ACTIVIDADES POR PASO CRITICO
B6: POA: | D6: PRIMER POA
B7: Nombre OA: | D7: =+Caratula!C7 -> ASOCIACION DE PRODUCTORES AGROPECUARIOS MICROCUENCA NORTE RIO NUÑOA
B8: RUC: | D8: =+Caratula!J7 -> 20448433316
B9: Plan de Negocios: | D9: =+Caratula!C8 -> MEJORAMIENTO DEL MANEJO PRUDUCTIVO DE LA ALPACA
B11: # | C11: OBJETIVO ESPECIFICO | E11: ACTIVIDAD | F11: MEDIO DE VERIFICACIÓN | G11: UNIDAD DE MEDIDA | H11: META | I11: PC 01 | O11: PC 02
I12: 45749 | J12: 45779 | K12: 45810 | L12: 45840 | M12: 45871 | N12: 45902 | O12: 45932 | P12: 45963 | Q12: 45993 | R12: 46024 | S12: 46055 | T12: 46083
B13: 1 | C13: =+'Formato 01'!C12:I12 -> 1.1. Aplicar Técnicas de manejo adecuado de los rebaños de alpacas que permita incrementar gradualmente la ganacia de peso diario de 0.08 kg/día a 0.15 kg/día/ alpaca al 5to año | E13: ='Formato 01'!B13 -> Mallas ganaderas de 9 hilos por 100 metros | F13: Acta de Entrega Recepción | G13: Soles | H13: ='Formato 01'!M13 -> 185760 | K13: =H13 -> 185760
E14: ='Formato 01'!B14 -> Postes Metálicos de 1.98m x 1.15"con ancla tipo flecha de acero, acabado y pintado | F14: Acta de Entrega Recepción | G14: Soles | H14: ='Formato 01'!M14 -> 103680 | K14: =H14 -> 103680
E15: ='Formato 01'!B15 -> Tecle 2T | F15: Acta de Entrega Recepción | G15: Soles | H15: ='Formato 01'!M15 -> 2700 | K15: =H15 -> 2700
E16: Gripples medianos | F16: Acta de Entrega Recepción | G16: Soles | H16: ='Formato 01'!M16 -> 14580 | K16: =H16 -> 14580
E17: ='Formato 01'!B17 -> Grapha Galvanizada 1" | F17: Acta de Entrega Recepción | G17: Soles | H17: ='Formato 01'!M17 -> 1620 | K17: =H17 -> 1620
E18: Puertas | F18: Acta de Entrega Recepción | G18: Soles | H18: ='Formato 01'!M18 -> 42120 | K18: =H18 -> 42120
E19: Yeso Bolsa 30Kg | F19: Acta de Entrega Recepción | G19: Soles | H19: ='Formato 01'!M19 -> 135 | K19: =H19 -> 135
B20: 2 | C20: ='Formato 01'!C20 -> 1.2. Ampliar la oferta forrajera con la instalación de 54 ha de alfalfa y dactilys en la asociación al 2do año | E20: ='Formato 02A'!E20 -> Semilla de Alfalfa | F20: Acta de Entrega Recepción | G20: Soles | H20: ='Formato 01'!M21 -> 54000 | N20: =H20 -> 54000
E21: ='Formato 02A'!E21 -> Semilla de Dactilys Glomerata | F21: Acta de Entrega Recepción | G21: Soles | H21: ='Formato 01'!M22 -> 2700 | N21: =H21 -> 2700
E22: ='Formato 02A'!E22 -> Guano de las islas | F22: Acta de Entrega Recepción | G22: Soles | H22: ='Formato 01'!M23 -> 70200 | N22: =H22 -> 70200
B23: 3 | C23: =+'Formato 01'!C24:I24 -> 1.3.Reducir el porcentaje de mortalidad de 4% a 2% al 2do año | E23: ='Formato 01'!B25 -> Kit Veterinario | F23: Acta de Entrega Recepción | G23: Soles | H23: ='Formato 01'!M25 -> 6858 | N23: =H23 -> 6858
B24: 4 | C24: ='Formato 01'!C26:I26 -> 1.4. Desarrollar capacidades para una eficiente gestión comercial de organización | E24: ='Formato 01'!B27 -> Coordinador del PNT | F24: Informe | G24: Soles | H24: ='Formato 01'!M27 -> 18000 | L24: 2000 | M24: 2000 | N24: 2000 | O24: 2000 | P24: 2000 | Q24: 2000 | R24: 2000 | S24: 2000 | T24: 2000
E25: ='Formato 01'!B28 -> Formulación del PNT | F25: Informe | G25: Soles | H25: ='Formato 01'!M28 -> 10000 | J25: =H25 -> 10000 | L25: 0
C28: Fecha y Hora : 28/04/2025 05:20 p.m.

Sheet Formato 03
B5: FORMATO 03 - INDICADORES DE SEGUIMIENTO Y MONITOREO DEL PLAN DE NEGOCIO
B6: POA: | D6: PRIMER POA
B7: Nombre OA: | D7: =+Caratula!C7 -> ASOCIACION DE PRODUCTORES AGROPECUARIOS MICROCUENCA NORTE RIO NUÑOA
B8: RUC: | D8: =+Caratula!J7 -> 20448433316
B9: Plan de Negocios: | D9: =+Caratula!C8 -> MEJORAMIENTO DEL MANEJO PRUDUCTIVO DE LA ALPACA
C11: OBJETIVO ESPECÍFICO | E11: TIPO | F11: INDICADOR | G11: LINEA BASE | H11: META PN | I11: METAS DEL POA POR PASO CRÍTICO | K11: META DEL POA | L11: MEDIO DE VERIFICACIÓN
G12: AÑO 0 | H12: (3 años) | I12: PC 01 | J12: PC 02 | K12: Acumulado
C13: MEJORAMIENTO DEL MANEJO PRUDUCTIVO DE LA ALPACA | E13: PRODUCCIÓN (Alpacas en engorde - peso inicial) | F13: Numero Cabezas (alpacas) | G13: 778 | H13: 1799 | I13: =(778)*0.4 -> 311.2 | J13: =(778)*0.6 -> 466.8 | K13: =I13+J13 -> 778 | L13: Actas de registro de producción
F14: Kg/Cabeza | G14: 15 | H14: 15 | I14: 15 | J14: 15 | K14: 15 | L14: Actas de registro de producción
F15: Total / año | G15: =G13*G14 -> 11670 | H15: =H13*H14 -> 26985 | I15: =I13*I14 -> 4668 | J15: =J13*J14 -> 7002 | K15: =K13*K14 -> 11670 | L15: Actas de registro de producción
F16: Ampliación de la oferta forralera Ha | G16: 0 | H16: 54 | I16: 0 | J16: 54 | K16: 0 | L16: Actas de registro de producción
E17: PRODUCCIÓN (Alpacas en engorde - peso final) | F17: Kg/Cabeza | G17: 24.6 | H17: 28.5 | I17: 25.8 | J17: 25.8 | K17: 25.8 | L17: Actas de registro de producción
F18: Total / año | G18: =G13*G17 -> 19138.8 | H18: =H13*H17 -> 51271.5 | I18: =I13*I17 -> 8028.96 | J18: =J13*J17 -> 12043.44 | K18: =K13*K17 -> 20072.4 | L18: Actas de registro de producción
E19: PRODUCTIVIDAD | F19: Periodo de engorde/Días | G19: 120 | H19: 90 | I19: 120 | J19: 120 | K19: 120 | L19: Actas de registro de producción
F20: Rendimiento esperado en Kg/día | G20: 0.08 | H20: 0.15 | I20: 0.09 | J20: 0.09 | K20: 0.09 | L20: Actas de registro de producción
F21: Reducir el porcentaje de Motalidad al año | G21: 0.04 | H21: 0.02 | I21: 0.04 | J21: 0.04 | K21: 0.04 | L21: Actas de registro de producción
F22: Incremento del periodo (kg/alpaca) | G22: 9.6 | H22: 13.5 | I22: 10.8 | J22: 10.8 | K22: 10.8 | L22: Actas de registro de producción
F23: Costos de Producción S/ / alpaca | G23: 318 | H23: 260 | I23: 271 | J23: 271 | K23: 271 | L23: Actas de registro de producción
E24: INGRESOS POR PESO CARCASA | F24: Animal en Pie (Kg) - Peso Carcasa | G24: =G18 -> 19138.8 | H24: =H18 -> 51271.5 | I24: =I18 -> 8028.96 | J24: =J18 -> 12043.44 | K24: =K18 -> 20072.4 | L24: Actas de registro de producción
F25: Precio por Kg/S | G25: 14 | H25: 14 | I25: 14 | J25: 14 | K25: 14 | L25: Comprobantes de Venta
F26: Ingreso total (S/.) | G26: =G24*G25 -> 267943.2 | H26: =H24*H25 -> 717801 | I26: =I24*I25 -> 112405.44 | J26: =J24*J25 -> 168608.16 | K26: =K24*K25 -> 281013.6 | L26: Comprobantes de Venta
C27: Equipamiento para la realización de labores culturales oportunas | E27: JORNALES | F27: Jornales (N° de Jornales Año) | G27: =187*2 -> 374 | H27: =179*2 -> 358 | I27: =(185*2)/2 -> 185 | J27: =(185*2)/2 -> 185 | K27: =I27+J27 -> 370 | L27: Actas de Asistencia del personal
C28: Manejo y conservación de pastos naturañes | E28: IMPACTO AMBIENTAL | F28: Abonamiento de los campos de pastoreo con estiércol de las alpacas | G28: 0.35 | H28: 1 | I28: =H28/2 -> 0.5 | J28: =H28/2 -> 0.5 | K28: =I28+J28 -> 1 | L28: Informe de verificación
B29: NOTA: Los indicadores del presente formato, deberán estar expuestos y claramente sustentados dentro de los RTFs, así mismo, deberán estar directamente alineados a los indicadores del PNT.
B30: Fecha y Hora : 28/04/2025 05:20 p.m.

Sheet xxxxxxxxxx
B1: QQ/HA | C1: HA | D1: TOTAL QQ | E1: KG/HA | F1: TOTAL KG | G1: TOTAL t
A2: 0 | B2: 12 | C2: 44.5 | D2: =+B2*C2 -> 534 | E2: =+B2*55.2 -> 662.4 | F2: =+E2*C2 -> 29476.8 | G2: =+F2/1000 -> 29.4768
A3: 1 | B3: 16 | C3: 44.5 | D3: =+B3*C3 -> 712 | E3: =+B3*55.2 -> 883.2 | F3: =+E3*C3 -> 39302.4 | G3: =+F3/1000 -> 39.3024
A4: 2 | B4: 20 | C4: 44.5 | D4: =+B4*C4 -> 890 | E4: =+B4*55.2 -> 1104 | F4: =+E4*C4 -> 49128 | G4: =+F4/1000 -> 49.128
A5: 3 | B5: 24 | C5: 44.5 | D5: =+B5*C5 -> 1068 | E5: =+B5*55.2 -> 1324.8 | F5: =+E5*C5 -> 58953.6 | G5: =+F5/1000 -> 58.9536
A6: 4

Sheet Hoja1
H31: dj HASTA K GRADO DE CCONSANGUIEDAD
