Workbook

Sheet Caratula
C2: INFORMACIÓN GENERAL DEL PLAN OPERATIVO DEL PLAN DE NEGOCIOS DE ADOPCIÓN DE TECNOLOGÍA
A4: INFORMACIÓN GENERAL DEL PLAN DE NEGOCIO
A5: N° de Convenio: | C5: 012-2025- MIDAGRI-AGROIDEAS | E5: N° Acta de CD: | G5: 100-2023 | H5: Periodo de Trabajo: | J5: 12 meses
A7: Nombre de la Organización: | C7: ASOCIACION DE PRODUCTORES AGROPECUARIOS MICROCUENCA NORTE RIO NUÑOA | H7: RUC: | J7: 20448433316 | K7: N° de Socios: | L7: 27
A8: Nombre del Plan de Negocios: | C8: MEJORAMIENTO DEL MANEJO PRUDUCTIVO DE LA ALPACA | H8: Producto o Actividad: | J8: Engorde y venta de alpacas en Pie | K8: Has según PN: | L8: 2360.21
A10: GEOREFERENCIACIÓN DEL PLAN DE NEGOCIO
A11: Departamento | C11: Provincia | E11: Distrito | G11: Localidad | I11: Coordenadas Geográficas
A12: Puno | C12: Melgar | E12: Nuñoa | G12: Carabaya | I12: Latitud | K12: Longitud
A15: CRONOGRAMA DE EJECUCIÓN | G15: PLAN DE COFINANCIAMIENTO
B16: POA 2 | G16: CO Financiamiento | I16: POA 2: Presupuesto S/. | K16: %
B17: Fecha de Inicio | D17: Fecha de Fin | G17: AGROIDEAS (S/. ) | I17: =I19*K17 -> 3200 | K17: 0.8
A18: PC1 | B18: 46114 | D18: 02//10/2026 | G18: OA (S/. ) | I18: =I19*K18 -> 800 | K18: 0.2
A19: PC2 | B19: 46298 | D19: 46479 | G19: Total (S/. ) | I19: ='Formato 01'!M10 -> 4000 | K19: =SUM(K17:K18) -> 1
A23: Representante Legal de la OA | E23: Coordinador de la UR | I23: Jefatura de la UM
A32: Firma | E32: Firma | I32: Firma

Sheet Formato 01
C3: FORMATO 01 - PLAN DE ADQUISICIONES DE EQUIPOS, INSUMOS Y SERVICIOS
C4: POA: | E4: SEGUNDO POA
C5: Nombre OA: | E5: =+Caratula!C7 -> ASOCIACION DE PRODUCTORES AGROPECUARIOS MICROCUENCA NORTE RIO NUÑOA
C6: RUC: | E6: =+Caratula!J7 -> 20448433316
C7: Plan de Negocios: | E7: =+Caratula!C8 -> MEJORAMIENTO DEL MANEJO PRUDUCTIVO DE LA ALPACA
B8: Objetivo Especifico / Actividad | G8: Especificación del Bien / Servicio | J8: PRESUPUESTO APROBADO EN EL PLAN DE NEGOCIO | N8: PARTICIPACIÓN PRESUPUESTAL
J9: Unidad de Medida | K9: Cantidad | L9: Costo Unitario S/. | M9: Costo Total Aprobado S/. | N9: OPA S/. | O9: AGROIDEAS S/. | P9: PASO CRÍTICO
C10: TOTAL GENERAL | M10: =+M12 -> 4000 | N10: =+N12 -> 800 | O10: =O12 -> 3200
M11: Porcentaje de Cofinanciamiento | N11: =+N10/M10 -> 0.2 | O11: =+O10/M10 -> 0.8
C12: 1.4. Desarrollar capacidades para una eficiente gestión comercial de organización | J12: Sub Total 1.5. | M12: =SUM(M13:M13) -> 4000 | N12: =M12*0.2 -> 800 | O12: =M12*0.8 -> 3200
B13: Coordinador del PNT | G13: Modalidad: servicio contratado por 12 meses. Perfil profesional Profesional titulado en Medicina Veterinaria y Zootecnia, Ingeniero zootecnista, Ingeniero agrónomo Experiencia General: seis (6) años en proyectos productivos de desarrollo pecuario Expericiencia Específica: Mínimo 3 años en la implementación de proyectos productivos de desarrollo alpaquero. Conocimiento del desarrollo de la cadena productiva de alpacas en infraestructura productiva, praderas nativas, sanidad animal, manejo de rebaño, manejo reproductivo, mejoramiento genético, campaña de acopio de fibra, gestión organizativa y articulación comercial Idiomas: Castellano y de preferencia dominio de quechua Funciones principales: 1. Valida y reconstruye la línea base de la organización 2. Vela por el cumplimiento de los objetivos y POA del PNT 3. Asesora y acompaña a la junta directiva en la adquisición de bienes y servicios 4. Elabora el calendario de manejo y sanitario para la organización 5. Elabora el Plan de Capacitación del PNT 6. Elabora el Plan de Asistencia Técnica 7. Desarrollo la asistencia técnica personalizada a cada beneficiario 8. Planifica e implementa las campañas técnicas de empadre controlado, parición, destete, selección y saca de animales. 9. Planifica y ejecuta las campañas sanitarias 10. Elabora los informes del RTF de la organización y validad por la directiva alcanza el programa 11. Elabora su informe mensual de trabajo a la presidencia de la organización para su validación gestión respectiva | J13: Mes | K13: 2 | L13: 2000 | M13: =+K13*L13 -> 4000 | N13: =+M13*0.2 -> 800 | O13: =+M13*0.8 -> 3200 | P13: I PC
C15: Fecha y Hora : 28/04/2025 05:20 p.m.

Sheet Formato 02A
B5: FORMATO 02A - PROGRAMACIÓN FÍSICA DE ACTIVIDADES POR PASO CRITICO
B6: POA: | D6: SEGUNDO POA
B7: Nombre OA: | D7: =+Caratula!C7 -> ASOCIACION DE PRODUCTORES AGROPECUARIOS MICROCUENCA NORTE RIO NUÑOA
B8: RUC: | D8: =+Caratula!J7 -> 20448433316
B9: Plan de Negocios: | D9: =+Caratula!C8 -> MEJORAMIENTO DEL MANEJO PRUDUCTIVO DE LA ALPACA
B11: # | C11: OBJETIVO ESPECIFICO | E11: ACTIVIDAD | F11: MEDIO DE VERIFICACIÓN | G11: UNIDAD DE MEDIDA | H11: META | I11: PC 01 | O11: PC 02
I12: 46114 | J12: 46144 | K12: 46175 | L12: 46205 | M12: 46236 | N12: 46267 | O12: 46297 | P12: 46328 | Q12: 46358 | R12: 46389 | S12: 46420 | T12: 46448
B13: 4 | C13: ='Formato 01'!C12:I12 -> 1.4. Desarrollar capacidades para una eficiente gestión comercial de organización | E13: ='Formato 01'!B13 -> Coordinador del PNT | F13: Informe | G13: MES | H13: =+'Formato 01'!K13 -> 2 | I13: 1 | J13: 1
C16: Fecha y Hora : 28/04/2025 05:20 p.m.

Sheet Formato 02B
B5: FORMATO 02B - PROGRAMACIÓN FINANCIERA DE ACTIVIDADES POR PASO CRITICO
B6: POA: | D6: SEGUNDO POA
B7: Nombre OA: | D7: =+Caratula!C7 -> ASOCIACION DE PRODUCTORES AGROPECUARIOS MICROCUENCA NORTE RIO NUÑOA
B8: RUC: | D8: =+Caratula!J7 -> 20448433316
B9: Plan de Negocios: | D9: =+Caratula!C8 -> MEJORAMIENTO DEL MANEJO PRUDUCTIVO DE LA ALPACA
B11: # | C11: OBJETIVO ESPECIFICO | E11: ACTIVIDAD | F11: MEDIO DE VERIFICACIÓN | G11: UNIDAD DE MEDIDA | H11: META | I11: PC 01 | O11: PC 02
I12: 46114 | J12: 46144 | K12: 46175 | L12: 46205 | M12: 46236 | N12: 46267 | O12: 46297 | P12: 46328 | Q12: 46358 | R12: 46389 | S12: 46420 | T12: 46448
B13: 4 | C13: ='Formato 01'!C12:I12 -> 1.4. Desarrollar capacidades para una eficiente gestión comercial de organización | E13: ='Formato 01'!B13 -> Coordinador del PNT | F13: Informe | G13: Soles | H13: ='Formato 01'!M13 -> 4000 | I13: 2000 | J13: 2000
C16: Fecha y Hora : 28/04/2025 05:20 p.m.

Sheet Formato 03
B5: FORMATO 03 - INDICADORES DE SEGUIMIENTO Y MONITOREO DEL PLAN DE NEGOCIO
B6: POA: | D6: SEGUNDO POA
B7: Nombre OA: | D7: =+Caratula!C7 -> ASOCIACION DE PRODUCTORES AGROPECUARIOS MICROCUENCA NORTE RIO NUÑOA
B8: RUC: | D8: =+Caratula!J7 -> 20448433316
B9: Plan de Negocios: | D9: =+Caratula!C8 -> MEJORAMIENTO DEL MANEJO PRUDUCTIVO DE LA ALPACA
C11: OBJETIVO ESPECÍFICO | E11: TIPO | F11: INDICADOR | G11: LINEA BASE | H11: META PN | I11: METAS DEL POA POR PASO CRÍTICO | K11: META DEL POA | L11: MEDIO DE VERIFICACIÓN
G12: AÑO 0 | H12: (3 años) | I12: PC 01 | J12: PC 02 | K12: Acumulado
C13: MEJORAMIENTO DEL MANEJO PRUDUCTIVO DE LA ALPACA | E13: PRODUCCIÓN (Alpacas en engorde - peso inicial) | F13: Numero Cabezas (alpacas) | G13: 778 | H13: 1799 | I13: =(1799)*0.4 -> 719.6 | J13: =(1799)*0.6 -> 1079.4 | K13: =I13+J13 -> 1799 | L13: Actas de registro de producción
F14: Kg/Cabeza | G14: 15 | H14: 15 | I14: 15 | J14: 15 | K14: 15 | L14: Actas de registro de producción
F15: Total / año | G15: =G13*G14 -> 11670 | H15: =H13*H14 -> 26985 | I15: =I13*I14 -> 10794 | J15: =J13*J14 -> 16191 | K15: =K13*K14 -> 26985 | L15: Actas de registro de producción
F16: Ampliación de la oferta forralera Ha | G16: 0 | H16: 0 | I16: 0 | J16: 0 | K16: 0 | L16: Actas de registro de producción
E17: PRODUCCIÓN (Alpacas en engorde - peso final) | F17: Kg/Cabeza | G17: 24.6 | H17: 28.5 | I17: 25.8 | J17: 25.8 | K17: 25.8 | L17: Actas de registro de producción
F18: Total / año | G18: =G13*G17 -> 19138.8 | H18: =H13*H17 -> 51271.5 | I18: =I13*I17 -> 18565.68 | J18: =J13*J17 -> 27848.52 | K18: =K13*K17 -> 46414.2 | L18: Actas de registro de producción
E19: PRODUCTIVIDAD | F19: Periodo de engorde/Días | G19: 120 | H19: 90 | I19: 90 | J19: 90 | K19: 90 | L19: Actas de registro de producción
F20: Rendimiento esperado en Kg/día | G20: 0.08 | H20: 0.15 | I20: 0.12 | J20: 0.12 | K20: 0.12 | L20: Actas de registro de producción
F21: Reducir el porcentaje de Motalidad al año | G21: 0.04 | H21: 0.02 | I21: 0.02 | J21: 0.02 | K21: 0.02 | L21: Actas de registro de producción
F22: Incremento del periodo (kg/alpaca) | G22: 9.6 | H22: 13.5 | I22: 10.8 | J22: 10.8 | K22: 10.8 | L22: Actas de registro de producción
F23: Costos de Producción S/ / alpaca | G23: 318 | H23: 260 | I23: 260 | J23: 260 | K23: 260 | L23: Actas de registro de producción
E24: INGRESOS POR PESO CARCASA | F24: Animal en Pie (Kg) - Peso Carcasa | G24: =G18 -> 19138.8 | H24: =H18 -> 51271.5 | I24: =I18 -> 18565.68 | J24: =J18 -> 27848.52 | K24: =K18 -> 46414.2 | L24: Actas de registro de producción
F25: Precio por Kg/S | G25: 14 | H25: 14 | I25: 14 | J25: 14 | K25: 14 | L25: Comprobantes de Venta
F26: Ingreso total (S/.) | G26: =G24*G25 -> 267943.2 | H26: =H24*H25 -> 717801 | I26: =I24*I25 -> 259919.52 | J26: =J24*J25 -> 389879.28 | K26: =K24*K25 -> 649798.8 | L26: Comprobantes de Venta
C27: Equipamiento para la realización de labores culturales oportunas | E27: JORNALES | F27: Jornales (N° de Jornales Año) | G27: =187*2 -> 374 | H27: =179*2 -> 358 | I27: =(185*2)/2 -> 185 | J27: =(185*2)/2 -> 185 | K27: =I27+J27 -> 370 | L27: Actas de Asistencia del personal
C28: Manejo y conservación de pastos naturañes | E28: IMPACTO AMBIENTAL | F28: Abonamiento de los campos de pastoreo con estiércol de las alpacas | G28: 0.35 | H28: 1 | I28: =H28/2 -> 0.5 | J28: =H28/2 -> 0.5 | K28: =I28+J28 -> 1 | L28: Informe de verificación
B29: NOTA: Los indicadores del presente formato, deberán estar expuestos y claramente sustentados dentro de los RTFs, así mismo, deberán estar directamente alineados a los indicadores del PNT.
B30: Fecha y Hora : 28/04/2025 05:20 p.m.

Sheet xxxxxxxxxx
B1: QQ/HA | C1: HA | D1: TOTAL QQ | E1: KG/HA | F1: TOTAL KG | G1: TOTAL t
A2: 0 | B2: 12 | C2: 44.5 | D2: =+B2*C2 -> 534 | E2: =+B2*55.2 -> 662.4 | F2: =+E2*C2 -> 29476.8 | G2: =+F2/1000 -> 29.4768
A3: 1 | B3: 16 | C3: 44.5 | D3: =+B3*C3 -> 712 | E3: =+B3*55.2 -> 883.2 | F3: =+E3*C3 -> 39302.4 | G3: =+F3/1000 -> 39.3024
A4: 2 | B4: 20 | C4: 44.5 | D4: =+B4*C4 -> 890 | E4: =+B4*55.2 -> 1104 | F4: =+E4*C4 -> 49128 | G4: =+F4/1000 -> 49.128
A5: 3 | B5: 24 | C5: 44.5 | D5: =+B5*C5 -> 1068 | E5: =+B5*55.2 -> 1324.8 | F5: =+E5*C5 -> 58953.6 | G5: =+F5/1000 -> 58.9536
A6: 4

Sheet Hoja1
H31: dj HASTA K GRADO DE CCONSANGUIEDAD
